{
    "current": {
        "title": "RUNAWAY",
        "artist": "FRANK JOSEPHS BAND"
    },
    "recent": [
        {
            "title": "WHERE LOVE GOES",
            "artist": "Dave Raynor"
        },
        {
            "title": "ALL I'VE GOT TO DO",
            "artist": "Flyin' Hawaiian Bro"
        },
        {
            "title": "ROSE IN THE VINE",
            "artist": "Harley"
        },
        {
            "title": "END OF THE DAY",
            "artist": "Manasus Strings"
        },
        {
            "title": "Tempted",
            "artist": "Harley Bros."
        },
        {
            "title": "IF WE FALL IN LOVE AGAIN",
            "artist": "Tom Kellock"
        },
        {
            "title": "Claudette",
            "artist": "Disk Eyes London"
        },
        {
            "title": "RAIN AND SHINE",
            "artist": "Jennifer Ivester"
        },
        {
            "title": "How Sweet it is",
            "artist": "Harley Music"
        },
        {
            "title": "THIS MASQUERADE",
            "artist": "DERRICK CHASE"
        }
    ]
}