{
    "current": {
        "title": "WELCOME TO MY WORLD",
        "artist": "Kevin Madill-Nashville"
    },
    "recent": [
        {
            "title": "My Favorite Mistake",
            "artist": "Frank Josephs"
        },
        {
            "title": "HOT SAUCE",
            "artist": "Eric Tingstad"
        },
        {
            "title": "You Make Lovin' Fun",
            "artist": "Harley Bros."
        },
        {
            "title": "DREAMBOAT ANNIE",
            "artist": "CHAD STONE BAND"
        },
        {
            "title": "DELIVER ME FROM MY MIND",
            "artist": "Andy Suzuki"
        },
        {
            "title": "SAD SONGS SAY SO MUCH",
            "artist": "TOM KELLOCK'S BTU"
        },
        {
            "title": "CRAZY LITTLE THING CALLED LOVE",
            "artist": "Harley Brothers"
        },
        {
            "title": "STUBBORN KIND OF FELLOW",
            "artist": "Crescenta Valley Boys"
        },
        {
            "title": "YOU'RE THE INSPIRATION",
            "artist": "FRANK JOSEPHS BAND"
        },
        {
            "title": "TIL I HEAR IT FROM YOU",
            "artist": "FLYIN' HAWAIIN BRO"
        }
    ]
}