{
    "current": {
        "title": "I WILL",
        "artist": "Josephs Band"
    },
    "recent": [
        {
            "title": "FOR ELFI",
            "artist": "Nick Manson"
        },
        {
            "title": "Ooh Baby Baby",
            "artist": "Crescenta Valley Boys"
        },
        {
            "title": "Fool on the Hill",
            "artist": "Los Devlin Strings"
        },
        {
            "title": "DESAFINADO",
            "artist": "BRAD ALLISON"
        },
        {
            "title": "Sun King",
            "artist": "San Francisco"
        },
        {
            "title": "Shooting Star",
            "artist": "Dave Raynor"
        },
        {
            "title": "COME FLY WITH ME",
            "artist": "Harley"
        },
        {
            "title": "CLOUDY",
            "artist": "NORTHPOINT"
        },
        {
            "title": "DON'T ASK MY NEIGHBOR",
            "artist": "STRINGS BY ANDY"
        },
        {
            "title": "I'm Happy Just to Dance with You",
            "artist": "Disk Eyes London"
        }
    ]
}