{
    "current": {
        "title": "APRIL BLUES",
        "artist": "Chatsworth Acoustic Band"
    },
    "recent": [
        {
            "title": "GOT TO GIVE IT UP",
            "artist": "STANDING PATT MUSIC"
        },
        {
            "title": "SAY YOU LOVE ME",
            "artist": "Josephs Band"
        },
        {
            "title": "I.G.Y. ( WHAT A BEAUTIFUL WORLD)",
            "artist": "CAMERON"
        },
        {
            "title": "Fly'n",
            "artist": "Dave Raynor"
        },
        {
            "title": "I JUST WANNA STOP",
            "artist": "MANASUS MUSIC"
        },
        {
            "title": "TROLLY CAR",
            "artist": "Jennifer Ivester"
        },
        {
            "title": "APPALACHIA CALLING",
            "artist": "Eric Tingstad"
        },
        {
            "title": "YOUNG ENOUGH TO KNOW",
            "artist": "Andy Suzuki"
        },
        {
            "title": "DON'T ASK MY NEIGHBOR",
            "artist": "STRINGS BY ANDY"
        },
        {
            "title": "YOU'RE THE INSPIRATION",
            "artist": "FRANK JOSEPHS BAND"
        }
    ]
}