{
    "current": {
        "title": "ONSTREAM",
        "artist": "Frank Joseph's Group"
    },
    "recent": [
        {
            "title": "SOMETHING THAT WE DO",
            "artist": "Harley Music"
        },
        {
            "title": "You're the Best Thing",
            "artist": "DAVE PATT"
        },
        {
            "title": "Yesterday",
            "artist": "Josephs Band"
        },
        {
            "title": "GIMME LITTLE SIGN",
            "artist": "STANDING PATT MUSIC"
        },
        {
            "title": "NEW BEGINNING",
            "artist": "RICK SCHMUNK"
        },
        {
            "title": "You Are My Destiny",
            "artist": "Los Devlin Strings"
        },
        {
            "title": "DON'T WANNA LOSE YOU",
            "artist": "Curtis Brengle"
        },
        {
            "title": "LIFE IS BUT A DREAM",
            "artist": "Devlin's Strings"
        },
        {
            "title": "BAD SNEAKERS",
            "artist": "LENNY MOORE"
        },
        {
            "title": "Ain't Nothing Like the Real Thing",
            "artist": "MANASUS MUSIC"
        }
    ]
}