{
    "current": {
        "title": "HEY GIRL",
        "artist": "ANDY SUZUKI/NICK MANSON"
    },
    "recent": [
        {
            "title": "SMOOTH OPERATOR",
            "artist": "Josephs Band"
        },
        {
            "title": "WHENEVER YOU'RE ON MY MIND",
            "artist": "Clair Marlo"
        },
        {
            "title": "CRAZY LITTLE THING CALLED LOVE",
            "artist": "Harley Brothers"
        },
        {
            "title": "Heartbreak Hotel",
            "artist": "Crescenta Valley Boys"
        },
        {
            "title": "DESAFINADO",
            "artist": "BRAD ALLISON"
        },
        {
            "title": "I SOLD MY HEART TO THE JUNKMAN",
            "artist": "Jim Devlin"
        },
        {
            "title": "WINDLESS",
            "artist": "Michael Strickland"
        },
        {
            "title": "Always Yours",
            "artist": "Dave Raynor"
        },
        {
            "title": "NEXT EVENT",
            "artist": "Chatsworth Acoustic Band"
        },
        {
            "title": "WELCOME TO MY WORLD",
            "artist": "Kevin Madill-Nashville"
        }
    ]
}