{
    "current": {
        "title": "MY FUNNY VALENTINE",
        "artist": "Manasus Strings"
    },
    "recent": [
        {
            "title": "ALL I'VE GOT TO DO",
            "artist": "Flyin' Hawaiian Bro"
        },
        {
            "title": "I.G.Y. ( WHAT A BEAUTIFUL WORLD)",
            "artist": "CAMERON"
        },
        {
            "title": "GOIN OUT OF MY HEAD",
            "artist": "Nick Manson"
        },
        {
            "title": "Tempted",
            "artist": "Harley Bros."
        },
        {
            "title": "I'M IN A PHILLY MOOD",
            "artist": "Mike Jaap"
        },
        {
            "title": "I Go Crazy",
            "artist": "David Patt"
        },
        {
            "title": "WELCOME TO MY WORLD",
            "artist": "Kevin Madill-Nashville"
        },
        {
            "title": "KRISTIANA",
            "artist": "Jerry Cortez"
        },
        {
            "title": "RAIN AND SHINE",
            "artist": "Jennifer Ivester"
        },
        {
            "title": "BLUE BOSSA",
            "artist": "BRAD ALLISON"
        }
    ]
}