{
    "current": {
        "title": "Elfi's Tune",
        "artist": "Dave Raynor"
    },
    "recent": [
        {
            "title": "ONSTREAM",
            "artist": "Frank Joseph's Group"
        },
        {
            "title": "SOMETIME BRAZIL",
            "artist": "Andy Suzuki"
        },
        {
            "title": "BACK STABBERS",
            "artist": "ANDY SUZUKI STRINGS"
        },
        {
            "title": "DON'T ASK MY NEIGHBOR",
            "artist": "STRINGS BY ANDY"
        },
        {
            "title": "CHAIN LIGHTNING",
            "artist": "Tom Politzer 93"
        },
        {
            "title": "LOVE WILL CONQUER ALL",
            "artist": "Tom Kellock"
        },
        {
            "title": "Turn Turn Turn",
            "artist": "John Morton"
        },
        {
            "title": "Yesterday",
            "artist": "Josephs Band"
        },
        {
            "title": "YOU ARE EVERYTHING",
            "artist": "STANDING PATT MUSIC"
        },
        {
            "title": "ALL ROADS LEAD TO YOU",
            "artist": "Kevin Madill-Nashville"
        }
    ]
}