{
    "current": {
        "title": "BEWILDERED",
        "artist": "MANSON STRINGS"
    },
    "recent": [
        {
            "title": "WILD AND FREE",
            "artist": "Chatsworth Acoustic Band"
        },
        {
            "title": "SUNNY CAME HOME",
            "artist": "MOORE and BRENGLE"
        },
        {
            "title": "SARA SMILE",
            "artist": "CHAD STONE BAND"
        },
        {
            "title": "IN WONDER",
            "artist": "Govi"
        },
        {
            "title": "RUNAWAY",
            "artist": "FRANK JOSEPHS BAND"
        },
        {
            "title": "FEEL LIKE MAKIN' LOVE",
            "artist": "Nick Manson"
        },
        {
            "title": "WHEN SUNNY GETS BLUE",
            "artist": "BRAD ALLISON"
        },
        {
            "title": "CAN WE TALK",
            "artist": "South Point"
        },
        {
            "title": "THAT'S WHAT FRIENDS ARE FOR",
            "artist": "North Point"
        },
        {
            "title": "RAIN AND SHINE",
            "artist": "Jennifer Ivester"
        }
    ]
}