{
    "current": {
        "title": "TIL I HEAR IT FROM YOU",
        "artist": "FLYIN' HAWAIIN BRO"
    },
    "recent": [
        {
            "title": "NEW YORK STATE OF MIND",
            "artist": "DERRICK CHASE"
        },
        {
            "title": "LIFE IS BUT A DREAM",
            "artist": "Devlin's Strings"
        },
        {
            "title": "SWEET LITTLE THANG",
            "artist": "Brian Withycombe"
        },
        {
            "title": "WHAT DOES IT TAKE",
            "artist": "JON GOFORTH"
        },
        {
            "title": "DON'T DREAM IT'S OVER",
            "artist": "Andre Mayeux"
        },
        {
            "title": "WHEN SUNNY GETS BLUE",
            "artist": "BRAD ALLISON"
        },
        {
            "title": "IF WE FALL IN LOVE AGAIN",
            "artist": "Tom Kellock"
        },
        {
            "title": "Walk On By",
            "artist": "Manson Music"
        },
        {
            "title": "COME FLY WITH ME",
            "artist": "Harley"
        },
        {
            "title": "How Sweet it is",
            "artist": "Harley Music"
        }
    ]
}