{
    "current": {
        "title": "FAIR TOMORROW",
        "artist": "Jerry Cortez"
    },
    "recent": [
        {
            "title": "ROSE IN THE VINE",
            "artist": "Harley"
        },
        {
            "title": "Till There Was You",
            "artist": "Dave Raynor"
        },
        {
            "title": "GIVING YOU THE BEST THAT I GOT",
            "artist": "Curtis Brengle"
        },
        {
            "title": "You Are My Destiny",
            "artist": "Los Devlin Strings"
        },
        {
            "title": "TORN",
            "artist": "Harley Music"
        },
        {
            "title": "HEAVEN",
            "artist": "North Point"
        },
        {
            "title": "ANOTHER SAD LOVE SONG",
            "artist": "Mike Jaap"
        },
        {
            "title": "JO JO",
            "artist": "ANDY SUZUKI STRINGS"
        },
        {
            "title": "STUBBORN KIND OF FELLOW",
            "artist": "Crescenta Valley Boys"
        },
        {
            "title": "THE FINER THINGS",
            "artist": "DAVE DYSART"
        }
    ]
}