{
    "current": {
        "title": "SOMETHING THAT WE DO",
        "artist": "Harley Music"
    },
    "recent": [
        {
            "title": "FAIR TOMORROW",
            "artist": "Jerry Cortez"
        },
        {
            "title": "I WANT TO THANK YOU",
            "artist": "MANASUS MUSIC"
        },
        {
            "title": "ALL I\u2019VE GOT TO DO",
            "artist": "Flyin\u2019 Hawaiian Bro"
        },
        {
            "title": "Elfi's Tune",
            "artist": "Dave Raynor"
        },
        {
            "title": "ONCE AND FUTURE",
            "artist": "Newhall Collective"
        },
        {
            "title": "TEARS FROM THE SUN",
            "artist": "PASERO/SUZUKI-HAWAII"
        },
        {
            "title": "MIRACLES",
            "artist": "North Point"
        },
        {
            "title": "I DON\u2019T WANNA BE ALONE",
            "artist": "MOORE and BRENGLE"
        },
        {
            "title": "THE FINER THINGS",
            "artist": "DAVE DYSART"
        },
        {
            "title": "ONSTREAM",
            "artist": "Frank Joseph\u2019s Group"
        }
    ]
}