{
    "current": {
        "title": "OLD OAK KNOLL",
        "artist": "Nick Manson"
    },
    "recent": [
        {
            "title": "HEY GIRL",
            "artist": "ANDY SUZUKI/NICK MANSON"
        },
        {
            "title": "I JUST WANNA STOP",
            "artist": "MANASUS MUSIC"
        },
        {
            "title": "THE FINER THINGS",
            "artist": "DAVE DYSART"
        },
        {
            "title": "WINDLESS",
            "artist": "Michael Strickland"
        },
        {
            "title": "I DON'T WANNA BE ALONE",
            "artist": "MOORE and BRENGLE"
        },
        {
            "title": "DON'T GO BREAKIN MY HEART",
            "artist": "Devlin's Strings"
        },
        {
            "title": "BEWILDERED",
            "artist": "MANSON STRINGS"
        },
        {
            "title": "BAD REPUTATION",
            "artist": "CHAD STONE BAND"
        },
        {
            "title": "GREEN FLOWER STREET",
            "artist": "Funtastic"
        },
        {
            "title": "(WILL YOU) COME BACK MY LOVE",
            "artist": "JOHN GOFORTH"
        }
    ]
}