{
    "current": {
        "title": "FOR ONCE IN OUR LIVES",
        "artist": "Andre Mayeux"
    },
    "recent": [
        {
            "title": "ROLL TO ME",
            "artist": "Harley Brothers"
        },
        {
            "title": "STAY (I MISSED YOU)",
            "artist": "Moro-Eden"
        },
        {
            "title": "WHERE IS THE LOVE",
            "artist": "Tom Kellock"
        },
        {
            "title": "Terpsichore",
            "artist": "Dave Keenan"
        },
        {
            "title": "GREEN FLOWER STREET",
            "artist": "Funtastic"
        },
        {
            "title": "Heaven On A Sunday",
            "artist": "John Morton"
        },
        {
            "title": "NEPTUNE",
            "artist": "Andy Suzuki"
        },
        {
            "title": "Claudette",
            "artist": "Disk Eyes London"
        },
        {
            "title": "WHAT'S GOIN ON",
            "artist": "Josephs Band"
        },
        {
            "title": "THESE DREAMS",
            "artist": "Curtis Brengle"
        }
    ]
}