{
    "current": {
        "title": "DIXIE MOON",
        "artist": "LENNY MOORE"
    },
    "recent": [
        {
            "title": "I'M IN A PHILLY MOOD",
            "artist": "Mike Jaap"
        },
        {
            "title": "DON'T DREAM IT'S OVER",
            "artist": "Andre Mayeux"
        },
        {
            "title": "GIRL WITH A RED CARNATION",
            "artist": "Acoustic Alchemy"
        },
        {
            "title": "BODY AND SOUL",
            "artist": "DAVE DYSART"
        },
        {
            "title": "SHAKE AND BAKE",
            "artist": "Newhall Collective"
        },
        {
            "title": "I THINK I'LL TELL HIM",
            "artist": "Andy Suzuki"
        },
        {
            "title": "GREEN FLOWER STREET",
            "artist": "Funtastic"
        },
        {
            "title": "CHAIN LIGHTNING",
            "artist": "Tom Politzer 93"
        },
        {
            "title": "SWEET CLAIRE",
            "artist": "Michael Strickland"
        },
        {
            "title": "MERCY MERCY ME",
            "artist": "Tom Kellock"
        }
    ]
}