{
    "current": {
        "title": "TROLLY CAR",
        "artist": "Jennifer Ivester"
    },
    "recent": [
        {
            "title": "I TURN TO YOU",
            "artist": "Daniel Ho"
        },
        {
            "title": "SAVING ALL MY LOVE FOR YOU",
            "artist": "NORTHPOINT"
        },
        {
            "title": "SOMEWHERE IN THE WORLD",
            "artist": "David Patt"
        },
        {
            "title": "Long Ago",
            "artist": "Dave Keenan"
        },
        {
            "title": "LAUGHTER IN THE RAIN",
            "artist": "Nick Manson"
        },
        {
            "title": "FOOLISH HEART",
            "artist": "Curtis Brengle"
        },
        {
            "title": "YOU'RE THE INSPIRATION",
            "artist": "FRANK JOSEPHS BAND"
        },
        {
            "title": "FOREVER MORE",
            "artist": "MOORE and BRENGLE"
        },
        {
            "title": "JULIA",
            "artist": "North Point"
        },
        {
            "title": "NEVER ENDING SONG OF LOVE",
            "artist": "DUKE OF MORTON"
        }
    ]
}