{
    "current": {
        "title": "JULIA",
        "artist": "North Point"
    },
    "recent": [
        {
            "title": "IT'S ALL ABOUT YOU",
            "artist": "FUNTASTIK"
        },
        {
            "title": "FOR ELFI",
            "artist": "Nick Manson"
        },
        {
            "title": "ALL I'VE GOT TO DO",
            "artist": "Flyin' Hawaiian Bro"
        },
        {
            "title": "YOU'RE THE INSPIRATION",
            "artist": "FRANK JOSEPHS BAND"
        },
        {
            "title": "DREAMLOVER",
            "artist": "It's Lenny Moore"
        },
        {
            "title": "I'LL BE OVER YOU",
            "artist": "Daniel Ho"
        },
        {
            "title": "Walton On Thames",
            "artist": "Jerry Cortez"
        },
        {
            "title": "SILVER SPRINGS",
            "artist": "Harley Brothers"
        },
        {
            "title": "I Only Have Eyes for You",
            "artist": "Politzer/Withycombe"
        },
        {
            "title": "Earl's Tune",
            "artist": "Dave Raynor"
        }
    ]
}