{
    "current": {
        "title": "WHEN SUNNY GETS BLUE",
        "artist": "BRAD ALLISON"
    },
    "recent": [
        {
            "title": "BAD SNEAKERS",
            "artist": "LENNY MOORE"
        },
        {
            "title": "JO JO",
            "artist": "ANDY SUZUKI STRINGS"
        },
        {
            "title": "SMOOTH OPERATOR",
            "artist": "Josephs Band"
        },
        {
            "title": "GAUCHO",
            "artist": "North Point"
        },
        {
            "title": "Love Of My Life",
            "artist": "Andre Mayeux"
        },
        {
            "title": "MAGNOLIA",
            "artist": "Funtastic"
        },
        {
            "title": "I THINK I'LL TELL HIM",
            "artist": "Andy Suzuki"
        },
        {
            "title": "THESE DREAMS",
            "artist": "Curtis Brengle"
        },
        {
            "title": "You Are My Destiny",
            "artist": "Los Devlin Strings"
        },
        {
            "title": "TIL I HEAR IT FROM YOU",
            "artist": "FLYIN' HAWAIIN BRO"
        }
    ]
}