{
    "current": {
        "title": "(WILL YOU) COME BACK MY LOVE",
        "artist": "JOHN GOFORTH"
    },
    "recent": [
        {
            "title": "Millennium",
            "artist": "Harley Brothers"
        },
        {
            "title": "HAKUNA MATATA",
            "artist": "Josephs Band"
        },
        {
            "title": "I GOTTA RUN",
            "artist": "John Morton"
        },
        {
            "title": "HALF A MINUTE",
            "artist": "FLYIN' HAWAIIN BRO"
        },
        {
            "title": "RUBY BABY",
            "artist": "Funtastic"
        },
        {
            "title": "MERCY MERCY ME",
            "artist": "Tom Kellock"
        },
        {
            "title": "BAD SNEAKERS",
            "artist": "LENNY MOORE"
        },
        {
            "title": "FOR ONCE IN OUR LIVES",
            "artist": "Andre Mayeux"
        },
        {
            "title": "PROMISE AIN\u2019T ENOUGH",
            "artist": "ANDY SUZUKI/NICK MANSON"
        },
        {
            "title": "SOMETHING THAT WE DO",
            "artist": "Harley Music"
        }
    ]
}