{
    "current": {
        "title": "I'M IN A PHILLY MOOD",
        "artist": "Mike Jaap"
    },
    "recent": [
        {
            "title": "MORE THAN THIS",
            "artist": "Disk Eyes S.F."
        },
        {
            "title": "TIL I HEAR IT FROM YOU",
            "artist": "FLYIN' HAWAIIN BRO"
        },
        {
            "title": "ROLL TO ME",
            "artist": "Harley Brothers"
        },
        {
            "title": "ALL I WANNA DO",
            "artist": "Harley"
        },
        {
            "title": "THE STRANGER",
            "artist": "North Point"
        },
        {
            "title": "DON'T WANNA LOSE YOU",
            "artist": "Curtis Brengle"
        },
        {
            "title": "IT MAKES ME CRAZY",
            "artist": "Nick Manson"
        },
        {
            "title": "Long Ago",
            "artist": "Dave Keenan"
        },
        {
            "title": "BLUE BOSSA",
            "artist": "BRAD ALLISON"
        },
        {
            "title": "HEARD IT IN A LOVE SONG",
            "artist": "DUKE OF MORTON"
        }
    ]
}