{
    "current": {
        "title": "ORDINARY WORLD",
        "artist": "Devlin's Strings"
    },
    "recent": [
        {
            "title": "Claudette",
            "artist": "Disk Eyes London"
        },
        {
            "title": "BAD REPUTATION",
            "artist": "CHAD STONE BAND"
        },
        {
            "title": "HOW MUCH I FEEL",
            "artist": "CAMERON"
        },
        {
            "title": "LIVELY UP YOURSELF",
            "artist": "Tom Politzer"
        },
        {
            "title": "Ain't Nothing Like the Real Thing",
            "artist": "MANASUS MUSIC"
        },
        {
            "title": "Just Like This Train",
            "artist": "San Francisco"
        },
        {
            "title": "SWAY",
            "artist": "Harley"
        },
        {
            "title": "WELCOME TO MY WORLD",
            "artist": "Kevin Madill-Nashville"
        },
        {
            "title": "EVERY BEAT OF MY HEART",
            "artist": "FLYIN' HAWAIIN BRO"
        },
        {
            "title": "WHAT DOES IT TAKE",
            "artist": "JON GOFORTH"
        }
    ]
}