{
    "current": {
        "title": "Yesterday",
        "artist": "Josephs Band"
    },
    "recent": [
        {
            "title": "Ain't Nothing Like the Real Thing",
            "artist": "MANASUS MUSIC"
        },
        {
            "title": "Sun King",
            "artist": "San Francisco"
        },
        {
            "title": "BAD SNEAKERS",
            "artist": "LENNY MOORE"
        },
        {
            "title": "THANK YOU",
            "artist": "Disk Eyes S.F."
        },
        {
            "title": "ANOTHER SAD LOVE SONG",
            "artist": "Mike Jaap"
        },
        {
            "title": "DON'T ASK MY NEIGHBOR",
            "artist": "STRINGS BY ANDY"
        },
        {
            "title": "MERCY MERCY ME",
            "artist": "Tom Kellock"
        },
        {
            "title": "My Favorite Mistake",
            "artist": "Frank Josephs"
        },
        {
            "title": "Tempted",
            "artist": "Harley Bros."
        },
        {
            "title": "HEAVEN",
            "artist": "North Point"
        }
    ]
}