{
    "current": {
        "title": "EVERY BEAT OF MY HEART",
        "artist": "FLYIN' HAWAIIN BRO"
    },
    "recent": [
        {
            "title": "I'M IN A PHILLY MOOD",
            "artist": "Mike Jaap"
        },
        {
            "title": "NEXT EVENT",
            "artist": "Chatsworth Acoustic Band"
        },
        {
            "title": "STARDUST",
            "artist": "LENNY MOORE"
        },
        {
            "title": "SHAKE AND BAKE",
            "artist": "Newhall Collective"
        },
        {
            "title": "BEWILDERED",
            "artist": "MANSON STRINGS"
        },
        {
            "title": "GOT TO GIVE IT UP",
            "artist": "STANDING PATT MUSIC"
        },
        {
            "title": "IN A DAYDREAM",
            "artist": "Crescenta Valley Boys"
        },
        {
            "title": "SARA SMILE",
            "artist": "CHAD STONE BAND"
        },
        {
            "title": "I'LL NEVER FALL IN LOVE",
            "artist": "Andre Mayeux"
        },
        {
            "title": "SOMEWHERE IN THE WORLD",
            "artist": "David Patt"
        }
    ]
}