{
    "current": {
        "title": "DESAFINADO",
        "artist": "BRAD ALLISON"
    },
    "recent": [
        {
            "title": "HEARD IT IN A LOVE SONG",
            "artist": "DUKE OF MORTON"
        },
        {
            "title": "FOR ONCE IN MY LIFE",
            "artist": "Josephs Band"
        },
        {
            "title": "POETRY MAN",
            "artist": "CAMERON"
        },
        {
            "title": "SLEEPING CAT DANCE",
            "artist": "Nick Manson"
        },
        {
            "title": "GIRL WITH A RED CARNATION",
            "artist": "Acoustic Alchemy"
        },
        {
            "title": "WHAT DOES IT TAKE",
            "artist": "JON GOFORTH"
        },
        {
            "title": "I Only Have Eyes for You",
            "artist": "Politzer/Withycombe"
        },
        {
            "title": "Wait So Long",
            "artist": "Dave Raynor"
        },
        {
            "title": "Heaven On A Sunday",
            "artist": "John Morton"
        },
        {
            "title": "I Say a Little Prayer",
            "artist": "Harley Music"
        }
    ]
}