{
    "current": {
        "title": "SOME ENCHANTED EVENING",
        "artist": "Manasus Strings"
    },
    "recent": [
        {
            "title": "MIRACLES",
            "artist": "North Point"
        },
        {
            "title": "STUBBORN KIND OF FELLOW",
            "artist": "Crescenta Valley Boys"
        },
        {
            "title": "RUBY BABY",
            "artist": "Funtastic"
        },
        {
            "title": "Sweet Seasons",
            "artist": "Harley Bros."
        },
        {
            "title": "WELCOME TO MY WORLD",
            "artist": "Kevin Madill-Nashville"
        },
        {
            "title": "YOUR'E NO GOOD",
            "artist": "FLYIN' HAWAIIN BRO"
        },
        {
            "title": "THANK YOU",
            "artist": "Disk Eyes S.F."
        },
        {
            "title": "GOT TO GIVE IT UP",
            "artist": "STANDING PATT MUSIC"
        },
        {
            "title": "STAY (I MISSED YOU)",
            "artist": "Moro-Eden"
        },
        {
            "title": "SOMETHING THAT WE DO",
            "artist": "Harley Music"
        }
    ]
}